notion_transformer/__init__.py
notion_transformer-0.1.0.dist-info/WHEEL
notion_transformer-0.1.0.dist-info/METADATA
notion_transformer-0.1.0.dist-info/RECORD
