Metadata-Version: 2.3
Name: notion-transformer
Version: 0.1.0
Summary: A tool to transform Notion API page properties.
Author: Mila Frerichs
Author-email: Mila Frerichs <mila@milaferichs.de>
Requires-Python: >=3.9
